hlxjson.py
HLXJSON-1.1.0.dist-info/LICENSE
HLXJSON-1.1.0.dist-info/METADATA
HLXJSON-1.1.0.dist-info/WHEEL
HLXJSON-1.1.0.dist-info/top_level.txt
HLXJSON-1.1.0.dist-info/RECORD
