Metadata-Version: 2.1
Name: HLXJSON
Version: 1.1.0
Summary: Easily read and write JSON files! Note that version 1.0.0 doesnt support writing to JSON with already existing data. Version 1.0.0 just removes all data before writing.( All data is erased when you start the file with the "hlxjson.start(filename)" function.)
Home-page: UNKNOWN
Author: Xephonine // Hylaxe
License: UNKNOWN
Platform: UNKNOWN
Classifier: Programming Language :: Python :: 3
Classifier: License :: OSI Approved :: MIT License
Classifier: Operating System :: Android
Classifier: Operating System :: Microsoft
Classifier: Operating System :: Microsoft :: Windows
Classifier: Operating System :: OS Independent
Requires-Python: >=3.2
License-File: LICENSE
